sinapsis_huggingface_embeddings/__init__.py
sinapsis_huggingface_embeddings/helpers/__init__.py
sinapsis_huggingface_embeddings/helpers/tags.py
sinapsis_huggingface_embeddings/templates/__init__.py
sinapsis_huggingface_embeddings/templates/hugging_face_embedding_extractor.py
sinapsis_huggingface_embeddings/templates/speaker_embedding_from_audio.py
sinapsis_huggingface_embeddings-0.1.9.dist-info/licenses/LICENSE
sinapsis_huggingface_embeddings-0.1.9.dist-info/METADATA
sinapsis_huggingface_embeddings-0.1.9.dist-info/WHEEL
sinapsis_huggingface_embeddings-0.1.9.dist-info/top_level.txt
sinapsis_huggingface_embeddings-0.1.9.dist-info/RECORD
