Metadata-Version: 2.4
Name: sinapsis-huggingface-embeddings
Version: 0.1.9
Summary: Templates to generate and/or extract text and image embeddings using HuggingFace
Author-email: SinapsisAI <dev@sinapsis.tech>
Project-URL: Homepage, https://sinapsis.tech
Project-URL: Documentation, https://docs.sinapsis.tech/docs
Project-URL: Tutorials, https://docs.sinapsis.tech/tutorials
Project-URL: Repository, https://github.com/Sinapsis-AI/sinapsis-huggingface.git
Requires-Python: >=3.10
License-File: LICENSE
Requires-Dist: datasets>=3.2.0
Requires-Dist: llama-index>=0.12.14
Requires-Dist: llama-index-embeddings-huggingface>=0.5.1
Requires-Dist: sinapsis>=0.1.1
Requires-Dist: soundfile>=0.13.1
Requires-Dist: speechbrain>=1.0.2
Requires-Dist: torchaudio>=2.5.1
Requires-Dist: tree-sitter==0.20.2
Requires-Dist: tree-sitter-languages>=1.10.2
Dynamic: license-file
